text2beep/__init__.py
text2beep/__main__.py
text2beep/const.py
text2beep/core.py
text2beep/version.py
text2beep-0.1.0.dist-info/LICENSE.txt
text2beep-0.1.0.dist-info/METADATA
text2beep-0.1.0.dist-info/WHEEL
text2beep-0.1.0.dist-info/entry_points.txt
text2beep-0.1.0.dist-info/top_level.txt
text2beep-0.1.0.dist-info/RECORD
