Metadata-Version: 2.1
Name: text2beep
Version: 0.1.0
Summary: A CLI tool that converts plaintext sheet music to beeps.
Home-page: https://github.com/shniubobo/text2beep
Author: shniubobo
Author-email: shniubobo@outlook.com
License: GPL-3.0-or-later
Project-URL: Source, https://github.com/shniubobo/text2beep
Project-URL: Issue Tracker, https://github.com/shniubobo/text2beep/issues
Platform: UNKNOWN
Classifier: Development Status :: 4 - Beta
Classifier: Intended Audience :: End Users/Desktop
Classifier: License :: OSI Approved :: GNU General Public License v3 (GPLv3)
Classifier: Operating System :: OS Independent
Classifier: Topic :: Multimedia :: Sound/Audio :: Sound Synthesis
Classifier: Programming Language :: Python
Classifier: Programming Language :: Python :: 3 :: Only
Classifier: Programming Language :: Python :: 3.6
Classifier: Programming Language :: Python :: 3.7
Classifier: Programming Language :: Python :: 3.8
Classifier: Programming Language :: Python :: Implementation :: CPython
Requires-Python: >=3.6, <4
Requires-Dist: numpy (~=1.19.1)
Requires-Dist: sounddevice (~=0.4.0)
Provides-Extra: dev
Requires-Dist: coverage[toml] (~=5.2.1) ; extra == 'dev'
Requires-Dist: flake8 (~=3.8.3) ; extra == 'dev'
Requires-Dist: pytest (>=6.0) ; extra == 'dev'
Requires-Dist: pytest-cov (~=2.10.1) ; extra == 'dev'
Requires-Dist: pytest-timeout (~=1.4.2) ; extra == 'dev'
